MANIFEST.in
README.md
setup.py
photobackup_bottle/__init__.py
photobackup_bottle/init.py
photobackup_bottle/photobackup.py
photobackup_bottle.egg-info/PKG-INFO
photobackup_bottle.egg-info/SOURCES.txt
photobackup_bottle.egg-info/dependency_links.txt
photobackup_bottle.egg-info/entry_points.txt
photobackup_bottle.egg-info/requires.txt
photobackup_bottle.egg-info/top_level.txt