Metadata-Version: 1.1
Name: photobackup-bottle
Version: 0.1.0
Summary: The simplest PhotoBackup server, made with bottle
Home-page: https://photobackup.github.io/
Author: s13d
Author-email: photobackup@s13d.fr
License: UNKNOWN
Keywords: pictures photographs mobile backup
Platform: UNKNOWN
Classifier: Development Status :: 3 - Alpha
Classifier: Framework :: Bottle
Classifier: License :: OSI Approved :: GNU General Public License v2 (GPLv2)
Classifier: Programming Language :: Python :: 3.2
Classifier: Programming Language :: Python :: 3.3
Classifier: Programming Language :: Python :: 3.4
Classifier: Natural Language :: English
Classifier: Topic :: System :: Archiving :: Backup
